{
  "result_index": 0,
  "results": [
    {
      "final": true,
      "alternatives": [
        {
          "transcript": "aló ",
          "confidence": 0.97,
          "timestamps": [
            [
              "aló",
              9.43,
              9.95
            ]
          ]
        }
      ]
    },
    {
      "final": true,
      "alternatives": [
        {
          "transcript": "buenas tardes por favor señor david andrés garcía ",
          "confidence": 1.0,
          "timestamps": [
            [
              "buenas",
              11.73,
              12.05
            ],
            [
              "tardes",
              12.05,
              12.38
            ],
            [
              "por",
              12.38,
              12.51
            ],
            [
              "favor",
              12.51,
              12.74
            ],
            [
              "señor",
              12.74,
              13.06
            ],
            [
              "david",
              13.06,
              13.4
            ],
            [
              "andrés",
              13.4,
              13.77
            ],
            [
              "garcía",
              13.77,
              14.27
            ]
          ]
        }
      ]
    },
    {
      "final": true,
      "alternatives": [
        {
          "transcript": "con el señor david como está la tarde de hoy habla paula parra su asesora de bancolombia en alianza con jesse como miley muy bien bien steve muy bien de preguntas en es un es señor davis pues en nosotros queremos dar la bienvenida por nuevamente confiar en el banco bancolombia perniciosos entidad financiera cuerdo a sus días se comunicaron con ustedes porque precisamente como bienvenida se está entregando la oportunidad empezar a manejar su servicio domiciliario por emergencias desde la comuna de su casa tanto para usted como para toda su familia en primero segundo gran consanguinidad quería sabes ya había revisado la página qué duda tiene para poder acciones servicios ",
          "confidence": 0.83,
          "timestamps": [
            [
              "con",
              15.27,
              15.55
            ],
            [
              "el",
              15.55,
              15.9
            ],
            [
              "señor",
              16.9,
              17.17
            ],
            [
              "david",
              17.17,
              17.46
            ],
            [
              "como",
              17.46,
              17.68
            ],
            [
              "está",
              17.68,
              17.84
            ],
            [
              "la",
              17.84,
              17.94
            ],
            [
              "tarde",
              17.94,
              18.23
            ],
            [
              "de",
              18.23,
              18.36
            ],
            [
              "hoy",
              18.36,
              18.55
            ],
            [
              "habla",
              18.55,
              18.73
            ],
            [
              "paula",
              18.73,
              19.08
            ],
            [
              "parra",
              19.08,
              19.57
            ],
            [
              "su",
              19.74,
              20.03
            ],
            [
              "asesora",
              20.03,
              20.45
            ],
            [
              "de",
              20.45,
              20.55
            ],
            [
              "bancolombia",
              20.55,
              21.28
            ],
            [
              "en",
              21.31,
              21.46
            ],
            [
              "alianza",
              21.46,
              21.82
            ],
            [
              "con",
              21.82,
              22.02
            ],
            [
              "jesse",
              22.02,
              22.6
            ],
            [
              "como",
              23.23,
              23.46
            ],
            [
              "miley",
              23.46,
              23.78
            ],
            [
              "muy",
              23.81,
              23.94
            ],
            [
              "bien",
              23.94,
              24.33
            ],
            [
              "bien",
              24.59,
              24.99
            ],
            [
              "steve",
              24.99,
              25.42
            ],
            [
              "muy",
              26.15,
              26.44
            ],
            [
              "bien",
              26.44,
              26.68
            ],
            [
              "de",
              26.68,
              26.99
            ],
            [
              "preguntas",
              26.99,
              28.01
            ],
            [
              "en",
              28.04,
              28.2
            ],
            [
              "es",
              28.2,
              28.3
            ],
            [
              "un",
              28.3,
              28.49
            ],
            [
              "es",
              28.49,
              28.59
            ],
            [
              "señor",
              28.59,
              28.86
            ],
            [
              "davis",
              28.86,
              29.17
            ],
            [
              "pues",
              29.17,
              29.39
            ],
            [
              "en",
              29.42,
              29.58
            ],
            [
              "nosotros",
              29.58,
              29.91
            ],
            [
              "queremos",
              29.91,
              30.21
            ],
            [
              "dar",
              30.21,
              30.37
            ],
            [
              "la",
              30.37,
              30.48
            ],
            [
              "bienvenida",
              30.48,
              31.07
            ],
            [
              "por",
              31.42,
              31.59
            ],
            [
              "nuevamente",
              31.59,
              32.05
            ],
            [
              "confiar",
              32.05,
              32.34
            ],
            [
              "en",
              32.34,
              32.45
            ],
            [
              "el",
              32.45,
              32.52
            ],
            [
              "banco",
              32.52,
              32.8
            ],
            [
              "bancolombia",
              32.83,
              33.44
            ],
            [
              "perniciosos",
              33.44,
              34.11
            ],
            [
              "entidad",
              34.11,
              34.46
            ],
            [
              "financiera",
              34.46,
              35.17
            ],
            [
              "cuerdo",
              35.2,
              35.59
            ],
            [
              "a",
              36.08,
              36.19
            ],
            [
              "sus",
              36.19,
              36.5
            ],
            [
              "días",
              36.5,
              36.85
            ],
            [
              "se",
              36.85,
              37.02
            ],
            [
              "comunicaron",
              37.02,
              37.57
            ],
            [
              "con",
              37.57,
              37.73
            ],
            [
              "ustedes",
              37.73,
              38.32
            ],
            [
              "porque",
              38.35,
              38.61
            ],
            [
              "precisamente",
              38.61,
              39.11
            ],
            [
              "como",
              39.11,
              39.32
            ],
            [
              "bienvenida",
              39.32,
              39.86
            ],
            [
              "se",
              39.86,
              40.02
            ],
            [
              "está",
              40.02,
              40.17
            ],
            [
              "entregando",
              40.17,
              40.72
            ],
            [
              "la",
              40.72,
              40.79
            ],
            [
              "oportunidad",
              40.79,
              41.28
            ],
            [
              "empezar",
              41.28,
              41.59
            ],
            [
              "a",
              41.59,
              41.64
            ],
            [
              "manejar",
              41.64,
              42.1
            ],
            [
              "su",
              42.34,
              42.5
            ],
            [
              "servicio",
              42.5,
              43.02
            ],
            [
              "domiciliario",
              43.02,
              43.73
            ],
            [
              "por",
              43.73,
              43.89
            ],
            [
              "emergencias",
              43.89,
              44.44
            ],
            [
              "desde",
              44.47,
              44.73
            ],
            [
              "la",
              44.73,
              44.82
            ],
            [
              "comuna",
              44.82,
              45.1
            ],
            [
              "de",
              45.1,
              45.21
            ],
            [
              "su",
              45.21,
              45.34
            ],
            [
              "casa",
              45.34,
              45.79
            ],
            [
              "tanto",
              46.09,
              46.4
            ],
            [
              "para",
              46.4,
              46.59
            ],
            [
              "usted",
              46.59,
              46.81
            ],
            [
              "como",
              46.81,
              47.04
            ],
            [
              "para",
              47.04,
              47.25
            ],
            [
              "toda",
              47.25,
              47.46
            ],
            [
              "su",
              47.46,
              47.58
            ],
            [
              "familia",
              47.58,
              48.01
            ],
            [
              "en",
              48.04,
              48.2
            ],
            [
              "primero",
              48.2,
              48.58
            ],
            [
              "segundo",
              48.58,
              48.93
            ],
            [
              "gran",
              48.93,
              49.11
            ],
            [
              "consanguinidad",
              49.11,
              49.93
            ],
            [
              "quería",
              50.24,
              50.5
            ],
            [
              "sabes",
              50.5,
              50.77
            ],
            [
              "ya",
              50.77,
              50.88
            ],
            [
              "había",
              50.88,
              51.02
            ],
            [
              "revisado",
              51.02,
              51.35
            ],
            [
              "la",
              51.35,
              51.46
            ],
            [
              "página",
              51.46,
              52.04
            ],
            [
              "qué",
              52.04,
              52.21
            ],
            [
              "duda",
              52.21,
              52.47
            ],
            [
              "tiene",
              52.47,
              52.81
            ],
            [
              "para",
              52.81,
              52.98
            ],
            [
              "poder",
              52.98,
              53.18
            ],
            [
              "acciones",
              53.18,
              53.57
            ],
            [
              "servicios",
              53.57,
              54.04
            ]
          ]
        }
      ]
    },
    {
      "final": true,
      "alternatives": [
        {
          "transcript": "no la verdad es que no me interesa mucho su intención y en este momento estoy ocupado más bien con sus cosas de la oficina ",
          "confidence": 0.84,
          "timestamps": [
            [
              "no",
              56.59,
              56.97
            ],
            [
              "la",
              56.97,
              57.13
            ],
            [
              "verdad",
              57.13,
              57.46
            ],
            [
              "es",
              57.46,
              57.58
            ],
            [
              "que",
              57.58,
              57.72
            ],
            [
              "no",
              57.72,
              57.88
            ],
            [
              "me",
              57.88,
              57.96
            ],
            [
              "interesa",
              57.96,
              58.37
            ],
            [
              "mucho",
              58.37,
              58.63
            ],
            [
              "su",
              58.63,
              58.81
            ],
            [
              "intención",
              58.93,
              59.48
            ],
            [
              "y",
              59.64,
              59.81
            ],
            [
              "en",
              59.81,
              59.92
            ],
            [
              "este",
              59.92,
              60.1
            ],
            [
              "momento",
              60.1,
              60.33
            ],
            [
              "estoy",
              60.33,
              60.85
            ],
            [
              "ocupado",
              61.29,
              61.85
            ],
            [
              "más",
              61.85,
              62.02
            ],
            [
              "bien",
              62.02,
              62.33
            ],
            [
              "con",
              62.33,
              62.57
            ],
            [
              "sus",
              62.57,
              62.79
            ],
            [
              "cosas",
              62.82,
              63.12
            ],
            [
              "de",
              63.12,
              63.19
            ],
            [
              "la",
              63.19,
              63.27
            ],
            [
              "oficina",
              63.27,
              63.87
            ]
          ]
        }
      ]
    },
    {
      "final": true,
      "alternatives": [
        {
          "transcript": "sunny por qué me dice que no le interesa mucho estamos sólo de proteger sus vidas estamos hablando de evitar a toda costa de que tengo una emergencia tengo que ir a un e p s una cita las persigo seis horas expones una enfermera un virus con somos ahora en desuso puede cubrir a su hermanos si tiene hijos por supuesto esposa padres cuñado suegros vivos o no en la ciudad de rionegro señor davis algo que quiero que se tome en cuenta por favor es que precisamente como bienvenidas usted solamente por cuanto los veinticuatro mil pesos con iva incluido tarifa congeladas al momento de ser alguno de los servicios mencionados entre otros su no pagan cuota moderadora nico pago usando un promontorio cubertura es muy buen beneficio considere que porque toda su familia ",
          "confidence": 0.85,
          "timestamps": [
            [
              "sunny",
              64.82,
              65.45
            ],
            [
              "por",
              65.45,
              65.63
            ],
            [
              "qué",
              65.63,
              65.72
            ],
            [
              "me",
              65.72,
              65.81
            ],
            [
              "dice",
              65.81,
              65.95
            ],
            [
              "que",
              65.95,
              66.06
            ],
            [
              "no",
              66.06,
              66.17
            ],
            [
              "le",
              66.17,
              66.24
            ],
            [
              "interesa",
              66.24,
              66.58
            ],
            [
              "mucho",
              66.58,
              66.9
            ],
            [
              "estamos",
              66.9,
              67.18
            ],
            [
              "sólo",
              67.18,
              67.34
            ],
            [
              "de",
              67.34,
              67.5
            ],
            [
              "proteger",
              67.5,
              67.95
            ],
            [
              "sus",
              67.95,
              68.12
            ],
            [
              "vidas",
              68.12,
              68.83
            ],
            [
              "estamos",
              68.86,
              69.15
            ],
            [
              "hablando",
              69.15,
              69.45
            ],
            [
              "de",
              69.45,
              69.51
            ],
            [
              "evitar",
              69.51,
              69.84
            ],
            [
              "a",
              69.84,
              69.9
            ],
            [
              "toda",
              69.9,
              70.21
            ],
            [
              "costa",
              70.21,
              70.58
            ],
            [
              "de",
              70.58,
              70.68
            ],
            [
              "que",
              70.68,
              70.85
            ],
            [
              "tengo",
              70.85,
              71.05
            ],
            [
              "una",
              71.05,
              71.15
            ],
            [
              "emergencia",
              71.15,
              71.65
            ],
            [
              "tengo",
              71.65,
              71.88
            ],
            [
              "que",
              71.88,
              72.01
            ],
            [
              "ir",
              72.01,
              72.11
            ],
            [
              "a",
              72.11,
              72.15
            ],
            [
              "un",
              72.15,
              72.25
            ],
            [
              "e",
              72.25,
              72.34
            ],
            [
              "p",
              72.34,
              72.59
            ],
            [
              "s",
              72.59,
              72.94
            ],
            [
              "una",
              73.08,
              73.38
            ],
            [
              "cita",
              73.38,
              73.72
            ],
            [
              "las",
              73.72,
              73.85
            ],
            [
              "persigo",
              73.85,
              74.31
            ],
            [
              "seis",
              74.31,
              74.57
            ],
            [
              "horas",
              74.57,
              74.86
            ],
            [
              "expones",
              74.86,
              75.24
            ],
            [
              "una",
              75.24,
              75.38
            ],
            [
              "enfermera",
              75.38,
              75.77
            ],
            [
              "un",
              75.77,
              75.89
            ],
            [
              "virus",
              75.89,
              76.68
            ],
            [
              "con",
              76.71,
              76.92
            ],
            [
              "somos",
              76.92,
              77.17
            ],
            [
              "ahora",
              77.17,
              77.31
            ],
            [
              "en",
              77.31,
              77.37
            ],
            [
              "desuso",
              77.37,
              77.67
            ],
            [
              "puede",
              77.67,
              77.84
            ],
            [
              "cubrir",
              77.84,
              78.16
            ],
            [
              "a",
              78.16,
              78.21
            ],
            [
              "su",
              78.21,
              78.32
            ],
            [
              "hermanos",
              78.32,
              79.23
            ],
            [
              "si",
              79.26,
              79.39
            ],
            [
              "tiene",
              79.39,
              79.72
            ],
            [
              "hijos",
              79.72,
              79.99
            ],
            [
              "por",
              79.99,
              80.14
            ],
            [
              "supuesto",
              80.14,
              80.56
            ],
            [
              "esposa",
              80.56,
              81.31
            ],
            [
              "padres",
              81.51,
              82.12
            ],
            [
              "cuñado",
              82.12,
              82.79
            ],
            [
              "suegros",
              82.79,
              83.71
            ],
            [
              "vivos",
              83.74,
              84.05
            ],
            [
              "o",
              84.08,
              84.23
            ],
            [
              "no",
              84.23,
              84.45
            ],
            [
              "en",
              84.48,
              84.59
            ],
            [
              "la",
              84.59,
              84.68
            ],
            [
              "ciudad",
              84.68,
              84.94
            ],
            [
              "de",
              84.94,
              85.02
            ],
            [
              "rionegro",
              85.02,
              85.5
            ],
            [
              "señor",
              85.5,
              85.79
            ],
            [
              "davis",
              85.79,
              86.17
            ],
            [
              "algo",
              86.99,
              87.29
            ],
            [
              "que",
              87.29,
              87.42
            ],
            [
              "quiero",
              87.42,
              87.72
            ],
            [
              "que",
              87.72,
              87.89
            ],
            [
              "se",
              87.89,
              88.05
            ],
            [
              "tome",
              88.05,
              88.24
            ],
            [
              "en",
              88.24,
              88.32
            ],
            [
              "cuenta",
              88.32,
              88.6
            ],
            [
              "por",
              88.6,
              88.78
            ],
            [
              "favor",
              88.78,
              89.18
            ],
            [
              "es",
              89.23,
              89.39
            ],
            [
              "que",
              89.39,
              89.51
            ],
            [
              "precisamente",
              89.51,
              90.01
            ],
            [
              "como",
              90.01,
              90.23
            ],
            [
              "bienvenidas",
              90.23,
              90.91
            ],
            [
              "usted",
              90.98,
              91.33
            ],
            [
              "solamente",
              91.33,
              91.81
            ],
            [
              "por",
              91.81,
              91.94
            ],
            [
              "cuanto",
              91.94,
              92.18
            ],
            [
              "los",
              92.18,
              92.31
            ],
            [
              "veinticuatro",
              92.31,
              92.88
            ],
            [
              "mil",
              92.88,
              93.1
            ],
            [
              "pesos",
              93.1,
              93.54
            ],
            [
              "con",
              93.54,
              93.71
            ],
            [
              "iva",
              93.71,
              93.87
            ],
            [
              "incluido",
              93.87,
              94.35
            ],
            [
              "tarifa",
              94.35,
              94.73
            ],
            [
              "congeladas",
              94.73,
              95.39
            ],
            [
              "al",
              95.82,
              95.99
            ],
            [
              "momento",
              95.99,
              96.36
            ],
            [
              "de",
              96.36,
              96.59
            ],
            [
              "ser",
              96.59,
              96.75
            ],
            [
              "alguno",
              96.75,
              97.06
            ],
            [
              "de",
              97.06,
              97.12
            ],
            [
              "los",
              97.12,
              97.21
            ],
            [
              "servicios",
              97.21,
              97.61
            ],
            [
              "mencionados",
              97.61,
              98.22
            ],
            [
              "entre",
              98.22,
              98.56
            ],
            [
              "otros",
              98.56,
              99.14
            ],
            [
              "su",
              99.37,
              99.5
            ],
            [
              "no",
              99.5,
              99.61
            ],
            [
              "pagan",
              99.61,
              99.95
            ],
            [
              "cuota",
              99.95,
              100.28
            ],
            [
              "moderadora",
              100.28,
              100.93
            ],
            [
              "nico",
              100.93,
              101.27
            ],
            [
              "pago",
              101.27,
              101.55
            ],
            [
              "usando",
              101.55,
              101.86
            ],
            [
              "un",
              101.86,
              101.93
            ],
            [
              "promontorio",
              101.93,
              102.47
            ],
            [
              "cubertura",
              102.5,
              103.1
            ],
            [
              "es",
              103.94,
              104.11
            ],
            [
              "muy",
              104.11,
              104.37
            ],
            [
              "buen",
              104.37,
              104.58
            ],
            [
              "beneficio",
              104.58,
              105.03
            ],
            [
              "considere",
              105.03,
              105.67
            ],
            [
              "que",
              105.67,
              105.81
            ],
            [
              "porque",
              105.81,
              106.06
            ],
            [
              "toda",
              106.06,
              106.28
            ],
            [
              "su",
              106.28,
              106.39
            ],
            [
              "familia",
              106.39,
              106.85
            ]
          ]
        }
      ]
    },
    {
      "final": true,
      "alternatives": [
        {
          "transcript": "recuerde que tiene laboratorios en casas recuerde que tiene eres una ambulancia médica lisa apara trasladó nivel nacional para cualquier tipo de enfermizos porque tipo de emergencia tanto para su comparación familias ",
          "confidence": 0.87,
          "timestamps": [
            [
              "recuerde",
              107.84,
              108.29
            ],
            [
              "que",
              108.29,
              108.4
            ],
            [
              "tiene",
              108.4,
              108.67
            ],
            [
              "laboratorios",
              108.67,
              109.58
            ],
            [
              "en",
              109.8,
              109.99
            ],
            [
              "casas",
              109.99,
              111.0
            ],
            [
              "recuerde",
              111.03,
              111.48
            ],
            [
              "que",
              111.48,
              111.6
            ],
            [
              "tiene",
              111.6,
              111.86
            ],
            [
              "eres",
              111.86,
              112.08
            ],
            [
              "una",
              112.08,
              112.21
            ],
            [
              "ambulancia",
              112.21,
              112.62
            ],
            [
              "médica",
              112.62,
              112.93
            ],
            [
              "lisa",
              112.93,
              113.2
            ],
            [
              "apara",
              113.2,
              113.53
            ],
            [
              "trasladó",
              113.53,
              113.93
            ],
            [
              "nivel",
              113.93,
              114.18
            ],
            [
              "nacional",
              114.18,
              114.86
            ],
            [
              "para",
              114.9,
              115.1
            ],
            [
              "cualquier",
              115.1,
              115.4
            ],
            [
              "tipo",
              115.4,
              115.62
            ],
            [
              "de",
              115.62,
              115.68
            ],
            [
              "enfermizos",
              115.68,
              116.3
            ],
            [
              "porque",
              116.33,
              116.57
            ],
            [
              "tipo",
              116.57,
              116.75
            ],
            [
              "de",
              116.75,
              116.81
            ],
            [
              "emergencia",
              116.81,
              117.27
            ],
            [
              "tanto",
              117.27,
              117.52
            ],
            [
              "para",
              117.52,
              117.68
            ],
            [
              "su",
              117.68,
              117.8
            ],
            [
              "comparación",
              117.8,
              118.26
            ],
            [
              "familias",
              118.26,
              118.94
            ]
          ]
        }
      ]
    },
    {
      "final": true,
      "alternatives": [
        {
          "transcript": "terapia sin ",
          "confidence": 0.5,
          "timestamps": [
            [
              "terapia",
              119.75,
              120.14
            ],
            [
              "sin",
              120.14,
              120.41
            ]
          ]
        }
      ]
    }
  ],
  "speaker_labels": [
    {
      "from": 9.43,
      "to": 9.95,
      "speaker": 0,
      "confidence": 0.5,
      "final": false
    },
    {
      "from": 11.73,
      "to": 12.05,
      "speaker": 1,
      "confidence": 0.67,
      "final": false
    },
    {
      "from": 12.05,
      "to": 12.38,
      "speaker": 1,
      "confidence": 0.67,
      "final": false
    },
    {
      "from": 12.38,
      "to": 12.51,
      "speaker": 1,
      "confidence": 0.67,
      "final": false
    },
    {
      "from": 12.51,
      "to": 12.74,
      "speaker": 1,
      "confidence": 0.67,
      "final": false
    },
    {
      "from": 12.74,
      "to": 13.06,
      "speaker": 1,
      "confidence": 0.67,
      "final": false
    },
    {
      "from": 13.06,
      "to": 13.4,
      "speaker": 1,
      "confidence": 0.67,
      "final": false
    },
    {
      "from": 13.4,
      "to": 13.77,
      "speaker": 1,
      "confidence": 0.67,
      "final": false
    },
    {
      "from": 13.77,
      "to": 14.27,
      "speaker": 1,
      "confidence": 0.67,
      "final": false
    },
    {
      "from": 15.27,
      "to": 15.55,
      "speaker": 0,
      "confidence": 0.62,
      "final": false
    },
    {
      "from": 15.55,
      "to": 15.9,
      "speaker": 0,
      "confidence": 0.62,
      "final": false
    },
    {
      "from": 16.9,
      "to": 17.17,
      "speaker": 1,
      "confidence": 0.46,
      "final": false
    },
    {
      "from": 17.17,
      "to": 17.46,
      "speaker": 1,
      "confidence": 0.46,
      "final": false
    },
    {
      "from": 17.46,
      "to": 17.68,
      "speaker": 1,
      "confidence": 0.46,
      "final": false
    },
    {
      "from": 17.68,
      "to": 17.84,
      "speaker": 1,
      "confidence": 0.46,
      "final": false
    },
    {
      "from": 17.84,
      "to": 17.94,
      "speaker": 1,
      "confidence": 0.46,
      "final": false
    },
    {
      "from": 17.94,
      "to": 18.23,
      "speaker": 1,
      "confidence": 0.46,
      "final": false
    },
    {
      "from": 18.23,
      "to": 18.36,
      "speaker": 1,
      "confidence": 0.46,
      "final": false
    },
    {
      "from": 18.36,
      "to": 18.55,
      "speaker": 1,
      "confidence": 0.46,
      "final": false
    },
    {
      "from": 18.55,
      "to": 18.73,
      "speaker": 1,
      "confidence": 0.46,
      "final": false
    },
    {
      "from": 18.73,
      "to": 19.08,
      "speaker": 1,
      "confidence": 0.46,
      "final": false
    },
    {
      "from": 19.08,
      "to": 19.57,
      "speaker": 1,
      "confidence": 0.46,
      "final": false
    },
    {
      "from": 19.74,
      "to": 20.03,
      "speaker": 1,
      "confidence": 0.49,
      "final": false
    },
    {
      "from": 20.03,
      "to": 20.45,
      "speaker": 1,
      "confidence": 0.49,
      "final": false
    },
    {
      "from": 20.45,
      "to": 20.55,
      "speaker": 1,
      "confidence": 0.49,
      "final": false
    },
    {
      "from": 20.55,
      "to": 21.28,
      "speaker": 1,
      "confidence": 0.49,
      "final": false
    },
    {
      "from": 21.31,
      "to": 21.46,
      "speaker": 1,
      "confidence": 0.49,
      "final": false
    },
    {
      "from": 21.46,
      "to": 21.82,
      "speaker": 1,
      "confidence": 0.49,
      "final": false
    },
    {
      "from": 21.82,
      "to": 22.02,
      "speaker": 1,
      "confidence": 0.49,
      "final": false
    },
    {
      "from": 22.02,
      "to": 22.6,
      "speaker": 1,
      "confidence": 0.49,
      "final": false
    },
    {
      "from": 23.23,
      "to": 23.46,
      "speaker": 1,
      "confidence": 0.35,
      "final": false
    },
    {
      "from": 23.46,
      "to": 23.78,
      "speaker": 1,
      "confidence": 0.35,
      "final": false
    },
    {
      "from": 23.81,
      "to": 23.94,
      "speaker": 0,
      "confidence": 0.63,
      "final": false
    },
    {
      "from": 23.94,
      "to": 24.33,
      "speaker": 0,
      "confidence": 0.63,
      "final": false
    },
    {
      "from": 24.59,
      "to": 24.99,
      "speaker": 0,
      "confidence": 0.63,
      "final": false
    },
    {
      "from": 24.99,
      "to": 25.42,
      "speaker": 0,
      "confidence": 0.63,
      "final": false
    },
    {
      "from": 26.15,
      "to": 26.44,
      "speaker": 1,
      "confidence": 0.45,
      "final": false
    },
    {
      "from": 26.44,
      "to": 26.68,
      "speaker": 1,
      "confidence": 0.45,
      "final": false
    },
    {
      "from": 26.68,
      "to": 26.99,
      "speaker": 1,
      "confidence": 0.45,
      "final": false
    },
    {
      "from": 26.99,
      "to": 28.01,
      "speaker": 1,
      "confidence": 0.45,
      "final": false
    },
    {
      "from": 28.04,
      "to": 28.2,
      "speaker": 1,
      "confidence": 0.46,
      "final": false
    },
    {
      "from": 28.2,
      "to": 28.3,
      "speaker": 1,
      "confidence": 0.46,
      "final": false
    },
    {
      "from": 28.3,
      "to": 28.49,
      "speaker": 1,
      "confidence": 0.46,
      "final": false
    },
    {
      "from": 28.49,
      "to": 28.59,
      "speaker": 1,
      "confidence": 0.46,
      "final": false
    },
    {
      "from": 28.59,
      "to": 28.86,
      "speaker": 1,
      "confidence": 0.46,
      "final": false
    },
    {
      "from": 28.86,
      "to": 29.17,
      "speaker": 1,
      "confidence": 0.46,
      "final": false
    },
    {
      "from": 29.17,
      "to": 29.39,
      "speaker": 1,
      "confidence": 0.46,
      "final": false
    },
    {
      "from": 29.42,
      "to": 29.58,
      "speaker": 1,
      "confidence": 0.5,
      "final": false
    },
    {
      "from": 29.58,
      "to": 29.91,
      "speaker": 1,
      "confidence": 0.5,
      "final": false
    },
    {
      "from": 29.91,
      "to": 30.21,
      "speaker": 1,
      "confidence": 0.5,
      "final": false
    },
    {
      "from": 30.21,
      "to": 30.37,
      "speaker": 1,
      "confidence": 0.5,
      "final": false
    },
    {
      "from": 30.37,
      "to": 30.48,
      "speaker": 1,
      "confidence": 0.5,
      "final": false
    },
    {
      "from": 30.48,
      "to": 31.07,
      "speaker": 1,
      "confidence": 0.5,
      "final": false
    },
    {
      "from": 31.42,
      "to": 31.59,
      "speaker": 1,
      "confidence": 0.51,
      "final": false
    },
    {
      "from": 31.59,
      "to": 32.05,
      "speaker": 1,
      "confidence": 0.51,
      "final": false
    },
    {
      "from": 32.05,
      "to": 32.34,
      "speaker": 1,
      "confidence": 0.51,
      "final": false
    },
    {
      "from": 32.34,
      "to": 32.45,
      "speaker": 1,
      "confidence": 0.51,
      "final": false
    },
    {
      "from": 32.45,
      "to": 32.52,
      "speaker": 1,
      "confidence": 0.51,
      "final": false
    },
    {
      "from": 32.52,
      "to": 32.8,
      "speaker": 1,
      "confidence": 0.51,
      "final": false
    },
    {
      "from": 32.83,
      "to": 33.44,
      "speaker": 1,
      "confidence": 0.49,
      "final": false
    },
    {
      "from": 33.44,
      "to": 34.11,
      "speaker": 1,
      "confidence": 0.49,
      "final": false
    },
    {
      "from": 34.11,
      "to": 34.46,
      "speaker": 1,
      "confidence": 0.49,
      "final": false
    },
    {
      "from": 34.46,
      "to": 35.17,
      "speaker": 1,
      "confidence": 0.49,
      "final": false
    },
    {
      "from": 35.2,
      "to": 35.59,
      "speaker": 1,
      "confidence": 0.37,
      "final": false
    },
    {
      "from": 36.08,
      "to": 36.19,
      "speaker": 1,
      "confidence": 0.5,
      "final": false
    },
    {
      "from": 36.19,
      "to": 36.5,
      "speaker": 1,
      "confidence": 0.5,
      "final": false
    },
    {
      "from": 36.5,
      "to": 36.85,
      "speaker": 1,
      "confidence": 0.5,
      "final": false
    },
    {
      "from": 36.85,
      "to": 37.02,
      "speaker": 1,
      "confidence": 0.5,
      "final": false
    },
    {
      "from": 37.02,
      "to": 37.57,
      "speaker": 1,
      "confidence": 0.5,
      "final": false
    },
    {
      "from": 37.57,
      "to": 37.73,
      "speaker": 1,
      "confidence": 0.5,
      "final": false
    },
    {
      "from": 37.73,
      "to": 38.32,
      "speaker": 1,
      "confidence": 0.5,
      "final": false
    },
    {
      "from": 38.35,
      "to": 38.61,
      "speaker": 1,
      "confidence": 0.49,
      "final": false
    },
    {
      "from": 38.61,
      "to": 39.11,
      "speaker": 1,
      "confidence": 0.49,
      "final": false
    },
    {
      "from": 39.11,
      "to": 39.32,
      "speaker": 1,
      "confidence": 0.49,
      "final": false
    },
    {
      "from": 39.32,
      "to": 39.86,
      "speaker": 1,
      "confidence": 0.49,
      "final": false
    },
    {
      "from": 39.86,
      "to": 40.02,
      "speaker": 1,
      "confidence": 0.49,
      "final": false
    },
    {
      "from": 40.02,
      "to": 40.17,
      "speaker": 1,
      "confidence": 0.49,
      "final": false
    },
    {
      "from": 40.17,
      "to": 40.72,
      "speaker": 1,
      "confidence": 0.49,
      "final": false
    },
    {
      "from": 40.72,
      "to": 40.79,
      "speaker": 1,
      "confidence": 0.49,
      "final": false
    },
    {
      "from": 40.79,
      "to": 41.28,
      "speaker": 1,
      "confidence": 0.49,
      "final": false
    },
    {
      "from": 41.28,
      "to": 41.59,
      "speaker": 1,
      "confidence": 0.49,
      "final": false
    },
    {
      "from": 41.59,
      "to": 41.64,
      "speaker": 1,
      "confidence": 0.49,
      "final": false
    },
    {
      "from": 41.64,
      "to": 42.1,
      "speaker": 1,
      "confidence": 0.49,
      "final": false
    },
    {
      "from": 42.34,
      "to": 42.5,
      "speaker": 1,
      "confidence": 0.53,
      "final": false
    },
    {
      "from": 42.5,
      "to": 43.02,
      "speaker": 1,
      "confidence": 0.53,
      "final": false
    },
    {
      "from": 43.02,
      "to": 43.73,
      "speaker": 1,
      "confidence": 0.53,
      "final": false
    },
    {
      "from": 43.73,
      "to": 43.89,
      "speaker": 1,
      "confidence": 0.53,
      "final": false
    },
    {
      "from": 43.89,
      "to": 44.44,
      "speaker": 1,
      "confidence": 0.53,
      "final": false
    },
    {
      "from": 44.47,
      "to": 44.73,
      "speaker": 1,
      "confidence": 0.41,
      "final": false
    },
    {
      "from": 44.73,
      "to": 44.82,
      "speaker": 1,
      "confidence": 0.41,
      "final": false
    },
    {
      "from": 44.82,
      "to": 45.1,
      "speaker": 1,
      "confidence": 0.41,
      "final": false
    },
    {
      "from": 45.1,
      "to": 45.21,
      "speaker": 1,
      "confidence": 0.41,
      "final": false
    },
    {
      "from": 45.21,
      "to": 45.34,
      "speaker": 1,
      "confidence": 0.41,
      "final": false
    },
    {
      "from": 45.34,
      "to": 45.79,
      "speaker": 1,
      "confidence": 0.41,
      "final": false
    },
    {
      "from": 46.09,
      "to": 46.4,
      "speaker": 1,
      "confidence": 0.48,
      "final": false
    },
    {
      "from": 46.4,
      "to": 46.59,
      "speaker": 1,
      "confidence": 0.48,
      "final": false
    },
    {
      "from": 46.59,
      "to": 46.81,
      "speaker": 1,
      "confidence": 0.48,
      "final": false
    },
    {
      "from": 46.81,
      "to": 47.04,
      "speaker": 1,
      "confidence": 0.48,
      "final": false
    },
    {
      "from": 47.04,
      "to": 47.25,
      "speaker": 1,
      "confidence": 0.48,
      "final": false
    },
    {
      "from": 47.25,
      "to": 47.46,
      "speaker": 1,
      "confidence": 0.48,
      "final": false
    },
    {
      "from": 47.46,
      "to": 47.58,
      "speaker": 1,
      "confidence": 0.48,
      "final": false
    },
    {
      "from": 47.58,
      "to": 48.01,
      "speaker": 1,
      "confidence": 0.48,
      "final": false
    },
    {
      "from": 48.04,
      "to": 48.2,
      "speaker": 1,
      "confidence": 0.37,
      "final": false
    },
    {
      "from": 48.2,
      "to": 48.58,
      "speaker": 1,
      "confidence": 0.37,
      "final": false
    },
    {
      "from": 48.58,
      "to": 48.93,
      "speaker": 1,
      "confidence": 0.37,
      "final": false
    },
    {
      "from": 48.93,
      "to": 49.11,
      "speaker": 1,
      "confidence": 0.37,
      "final": false
    },
    {
      "from": 49.11,
      "to": 49.93,
      "speaker": 1,
      "confidence": 0.37,
      "final": false
    },
    {
      "from": 50.24,
      "to": 50.5,
      "speaker": 1,
      "confidence": 0.46,
      "final": false
    },
    {
      "from": 50.5,
      "to": 50.77,
      "speaker": 1,
      "confidence": 0.46,
      "final": false
    },
    {
      "from": 50.77,
      "to": 50.88,
      "speaker": 1,
      "confidence": 0.46,
      "final": false
    },
    {
      "from": 50.88,
      "to": 51.02,
      "speaker": 1,
      "confidence": 0.46,
      "final": false
    },
    {
      "from": 51.02,
      "to": 51.35,
      "speaker": 1,
      "confidence": 0.46,
      "final": false
    },
    {
      "from": 51.35,
      "to": 51.46,
      "speaker": 1,
      "confidence": 0.46,
      "final": false
    },
    {
      "from": 51.46,
      "to": 52.04,
      "speaker": 1,
      "confidence": 0.46,
      "final": false
    },
    {
      "from": 52.04,
      "to": 52.21,
      "speaker": 1,
      "confidence": 0.46,
      "final": false
    },
    {
      "from": 52.21,
      "to": 52.47,
      "speaker": 1,
      "confidence": 0.46,
      "final": false
    },
    {
      "from": 52.47,
      "to": 52.81,
      "speaker": 1,
      "confidence": 0.46,
      "final": false
    },
    {
      "from": 52.81,
      "to": 52.98,
      "speaker": 1,
      "confidence": 0.46,
      "final": false
    },
    {
      "from": 52.98,
      "to": 53.18,
      "speaker": 1,
      "confidence": 0.46,
      "final": false
    },
    {
      "from": 53.18,
      "to": 53.57,
      "speaker": 1,
      "confidence": 0.46,
      "final": false
    },
    {
      "from": 53.57,
      "to": 54.04,
      "speaker": 1,
      "confidence": 0.46,
      "final": false
    },
    {
      "from": 56.59,
      "to": 56.97,
      "speaker": 0,
      "confidence": 0.59,
      "final": false
    },
    {
      "from": 56.97,
      "to": 57.13,
      "speaker": 0,
      "confidence": 0.59,
      "final": false
    },
    {
      "from": 57.13,
      "to": 57.46,
      "speaker": 0,
      "confidence": 0.59,
      "final": false
    },
    {
      "from": 57.46,
      "to": 57.58,
      "speaker": 0,
      "confidence": 0.59,
      "final": false
    },
    {
      "from": 57.58,
      "to": 57.72,
      "speaker": 0,
      "confidence": 0.59,
      "final": false
    },
    {
      "from": 57.72,
      "to": 57.88,
      "speaker": 0,
      "confidence": 0.59,
      "final": false
    },
    {
      "from": 57.88,
      "to": 57.96,
      "speaker": 0,
      "confidence": 0.59,
      "final": false
    },
    {
      "from": 57.96,
      "to": 58.37,
      "speaker": 0,
      "confidence": 0.59,
      "final": false
    },
    {
      "from": 58.37,
      "to": 58.63,
      "speaker": 0,
      "confidence": 0.59,
      "final": false
    },
    {
      "from": 58.63,
      "to": 58.81,
      "speaker": 0,
      "confidence": 0.59,
      "final": false
    },
    {
      "from": 58.93,
      "to": 59.48,
      "speaker": 0,
      "confidence": 0.57,
      "final": false
    },
    {
      "from": 59.64,
      "to": 59.81,
      "speaker": 0,
      "confidence": 0.6,
      "final": false
    },
    {
      "from": 59.81,
      "to": 59.92,
      "speaker": 0,
      "confidence": 0.6,
      "final": false
    },
    {
      "from": 59.92,
      "to": 60.1,
      "speaker": 0,
      "confidence": 0.6,
      "final": false
    },
    {
      "from": 60.1,
      "to": 60.33,
      "speaker": 0,
      "confidence": 0.6,
      "final": false
    },
    {
      "from": 60.33,
      "to": 60.85,
      "speaker": 0,
      "confidence": 0.6,
      "final": false
    },
    {
      "from": 61.29,
      "to": 61.85,
      "speaker": 0,
      "confidence": 0.64,
      "final": false
    },
    {
      "from": 61.85,
      "to": 62.02,
      "speaker": 0,
      "confidence": 0.64,
      "final": false
    },
    {
      "from": 62.02,
      "to": 62.33,
      "speaker": 0,
      "confidence": 0.64,
      "final": false
    },
    {
      "from": 62.33,
      "to": 62.57,
      "speaker": 0,
      "confidence": 0.64,
      "final": false
    },
    {
      "from": 62.57,
      "to": 62.79,
      "speaker": 0,
      "confidence": 0.64,
      "final": false
    },
    {
      "from": 62.82,
      "to": 63.12,
      "speaker": 0,
      "confidence": 0.6,
      "final": false
    },
    {
      "from": 63.12,
      "to": 63.19,
      "speaker": 0,
      "confidence": 0.6,
      "final": false
    },
    {
      "from": 63.19,
      "to": 63.27,
      "speaker": 0,
      "confidence": 0.6,
      "final": false
    },
    {
      "from": 63.27,
      "to": 63.87,
      "speaker": 0,
      "confidence": 0.6,
      "final": false
    },
    {
      "from": 64.82,
      "to": 65.45,
      "speaker": 1,
      "confidence": 0.54,
      "final": false
    },
    {
      "from": 65.45,
      "to": 65.63,
      "speaker": 1,
      "confidence": 0.54,
      "final": false
    },
    {
      "from": 65.63,
      "to": 65.72,
      "speaker": 1,
      "confidence": 0.54,
      "final": false
    },
    {
      "from": 65.72,
      "to": 65.81,
      "speaker": 1,
      "confidence": 0.54,
      "final": false
    },
    {
      "from": 65.81,
      "to": 65.95,
      "speaker": 1,
      "confidence": 0.54,
      "final": false
    },
    {
      "from": 65.95,
      "to": 66.06,
      "speaker": 1,
      "confidence": 0.54,
      "final": false
    },
    {
      "from": 66.06,
      "to": 66.17,
      "speaker": 1,
      "confidence": 0.54,
      "final": false
    },
    {
      "from": 66.17,
      "to": 66.24,
      "speaker": 1,
      "confidence": 0.54,
      "final": false
    },
    {
      "from": 66.24,
      "to": 66.58,
      "speaker": 1,
      "confidence": 0.54,
      "final": false
    },
    {
      "from": 66.58,
      "to": 66.9,
      "speaker": 1,
      "confidence": 0.54,
      "final": false
    },
    {
      "from": 66.9,
      "to": 67.18,
      "speaker": 1,
      "confidence": 0.54,
      "final": false
    },
    {
      "from": 67.18,
      "to": 67.34,
      "speaker": 1,
      "confidence": 0.54,
      "final": false
    },
    {
      "from": 67.34,
      "to": 67.5,
      "speaker": 1,
      "confidence": 0.54,
      "final": false
    },
    {
      "from": 67.5,
      "to": 67.95,
      "speaker": 1,
      "confidence": 0.54,
      "final": false
    },
    {
      "from": 67.95,
      "to": 68.12,
      "speaker": 1,
      "confidence": 0.54,
      "final": false
    },
    {
      "from": 68.12,
      "to": 68.83,
      "speaker": 1,
      "confidence": 0.54,
      "final": false
    },
    {
      "from": 68.86,
      "to": 69.15,
      "speaker": 1,
      "confidence": 0.57,
      "final": false
    },
    {
      "from": 69.15,
      "to": 69.45,
      "speaker": 1,
      "confidence": 0.57,
      "final": false
    },
    {
      "from": 69.45,
      "to": 69.51,
      "speaker": 1,
      "confidence": 0.57,
      "final": false
    },
    {
      "from": 69.51,
      "to": 69.84,
      "speaker": 1,
      "confidence": 0.57,
      "final": false
    },
    {
      "from": 69.84,
      "to": 69.9,
      "speaker": 1,
      "confidence": 0.57,
      "final": false
    },
    {
      "from": 69.9,
      "to": 70.21,
      "speaker": 1,
      "confidence": 0.57,
      "final": false
    },
    {
      "from": 70.21,
      "to": 70.58,
      "speaker": 1,
      "confidence": 0.57,
      "final": false
    },
    {
      "from": 70.58,
      "to": 70.68,
      "speaker": 1,
      "confidence": 0.57,
      "final": false
    },
    {
      "from": 70.68,
      "to": 70.85,
      "speaker": 1,
      "confidence": 0.57,
      "final": false
    },
    {
      "from": 70.85,
      "to": 71.05,
      "speaker": 1,
      "confidence": 0.57,
      "final": false
    },
    {
      "from": 71.05,
      "to": 71.15,
      "speaker": 1,
      "confidence": 0.57,
      "final": false
    },
    {
      "from": 71.15,
      "to": 71.65,
      "speaker": 1,
      "confidence": 0.57,
      "final": false
    },
    {
      "from": 71.65,
      "to": 71.88,
      "speaker": 1,
      "confidence": 0.57,
      "final": false
    },
    {
      "from": 71.88,
      "to": 72.01,
      "speaker": 1,
      "confidence": 0.57,
      "final": false
    },
    {
      "from": 72.01,
      "to": 72.11,
      "speaker": 1,
      "confidence": 0.57,
      "final": false
    },
    {
      "from": 72.11,
      "to": 72.15,
      "speaker": 1,
      "confidence": 0.57,
      "final": false
    },
    {
      "from": 72.15,
      "to": 72.25,
      "speaker": 1,
      "confidence": 0.57,
      "final": false
    },
    {
      "from": 72.25,
      "to": 72.34,
      "speaker": 1,
      "confidence": 0.57,
      "final": false
    },
    {
      "from": 72.34,
      "to": 72.59,
      "speaker": 1,
      "confidence": 0.57,
      "final": false
    },
    {
      "from": 72.59,
      "to": 72.94,
      "speaker": 1,
      "confidence": 0.57,
      "final": false
    },
    {
      "from": 73.08,
      "to": 73.38,
      "speaker": 1,
      "confidence": 0.56,
      "final": false
    },
    {
      "from": 73.38,
      "to": 73.72,
      "speaker": 1,
      "confidence": 0.56,
      "final": false
    },
    {
      "from": 73.72,
      "to": 73.85,
      "speaker": 1,
      "confidence": 0.56,
      "final": false
    },
    {
      "from": 73.85,
      "to": 74.31,
      "speaker": 1,
      "confidence": 0.56,
      "final": false
    },
    {
      "from": 74.31,
      "to": 74.57,
      "speaker": 1,
      "confidence": 0.56,
      "final": false
    },
    {
      "from": 74.57,
      "to": 74.86,
      "speaker": 1,
      "confidence": 0.56,
      "final": false
    },
    {
      "from": 74.86,
      "to": 75.24,
      "speaker": 1,
      "confidence": 0.56,
      "final": false
    },
    {
      "from": 75.24,
      "to": 75.38,
      "speaker": 1,
      "confidence": 0.56,
      "final": false
    },
    {
      "from": 75.38,
      "to": 75.77,
      "speaker": 1,
      "confidence": 0.56,
      "final": false
    },
    {
      "from": 75.77,
      "to": 75.89,
      "speaker": 1,
      "confidence": 0.56,
      "final": false
    },
    {
      "from": 75.89,
      "to": 76.68,
      "speaker": 1,
      "confidence": 0.56,
      "final": false
    },
    {
      "from": 76.71,
      "to": 76.92,
      "speaker": 1,
      "confidence": 0.5,
      "final": false
    },
    {
      "from": 76.92,
      "to": 77.17,
      "speaker": 1,
      "confidence": 0.5,
      "final": false
    },
    {
      "from": 77.17,
      "to": 77.31,
      "speaker": 1,
      "confidence": 0.5,
      "final": false
    },
    {
      "from": 77.31,
      "to": 77.37,
      "speaker": 1,
      "confidence": 0.5,
      "final": false
    },
    {
      "from": 77.37,
      "to": 77.67,
      "speaker": 1,
      "confidence": 0.5,
      "final": false
    },
    {
      "from": 77.67,
      "to": 77.84,
      "speaker": 1,
      "confidence": 0.5,
      "final": false
    },
    {
      "from": 77.84,
      "to": 78.16,
      "speaker": 1,
      "confidence": 0.5,
      "final": false
    },
    {
      "from": 78.16,
      "to": 78.21,
      "speaker": 1,
      "confidence": 0.5,
      "final": false
    },
    {
      "from": 78.21,
      "to": 78.32,
      "speaker": 1,
      "confidence": 0.5,
      "final": false
    },
    {
      "from": 78.32,
      "to": 79.23,
      "speaker": 1,
      "confidence": 0.5,
      "final": false
    },
    {
      "from": 79.26,
      "to": 79.39,
      "speaker": 1,
      "confidence": 0.53,
      "final": false
    },
    {
      "from": 79.39,
      "to": 79.72,
      "speaker": 1,
      "confidence": 0.53,
      "final": false
    },
    {
      "from": 79.72,
      "to": 79.99,
      "speaker": 1,
      "confidence": 0.53,
      "final": false
    },
    {
      "from": 79.99,
      "to": 80.14,
      "speaker": 1,
      "confidence": 0.53,
      "final": false
    },
    {
      "from": 80.14,
      "to": 80.56,
      "speaker": 1,
      "confidence": 0.53,
      "final": false
    },
    {
      "from": 80.56,
      "to": 81.31,
      "speaker": 1,
      "confidence": 0.53,
      "final": false
    },
    {
      "from": 81.51,
      "to": 82.12,
      "speaker": 1,
      "confidence": 0.45,
      "final": false
    },
    {
      "from": 82.12,
      "to": 82.79,
      "speaker": 1,
      "confidence": 0.45,
      "final": false
    },
    {
      "from": 82.79,
      "to": 83.71,
      "speaker": 1,
      "confidence": 0.45,
      "final": false
    },
    {
      "from": 83.74,
      "to": 84.05,
      "speaker": 1,
      "confidence": 0.43,
      "final": false
    },
    {
      "from": 84.08,
      "to": 84.23,
      "speaker": 1,
      "confidence": 0.41,
      "final": false
    },
    {
      "from": 84.23,
      "to": 84.45,
      "speaker": 1,
      "confidence": 0.41,
      "final": false
    },
    {
      "from": 84.48,
      "to": 84.59,
      "speaker": 1,
      "confidence": 0.46,
      "final": false
    },
    {
      "from": 84.59,
      "to": 84.68,
      "speaker": 1,
      "confidence": 0.46,
      "final": false
    },
    {
      "from": 84.68,
      "to": 84.94,
      "speaker": 1,
      "confidence": 0.46,
      "final": false
    },
    {
      "from": 84.94,
      "to": 85.02,
      "speaker": 1,
      "confidence": 0.46,
      "final": false
    },
    {
      "from": 85.02,
      "to": 85.5,
      "speaker": 1,
      "confidence": 0.46,
      "final": false
    },
    {
      "from": 85.5,
      "to": 85.79,
      "speaker": 1,
      "confidence": 0.46,
      "final": false
    },
    {
      "from": 85.79,
      "to": 86.17,
      "speaker": 1,
      "confidence": 0.46,
      "final": false
    },
    {
      "from": 86.99,
      "to": 87.29,
      "speaker": 1,
      "confidence": 0.5,
      "final": false
    },
    {
      "from": 87.29,
      "to": 87.42,
      "speaker": 1,
      "confidence": 0.5,
      "final": false
    },
    {
      "from": 87.42,
      "to": 87.72,
      "speaker": 1,
      "confidence": 0.5,
      "final": false
    },
    {
      "from": 87.72,
      "to": 87.89,
      "speaker": 1,
      "confidence": 0.5,
      "final": false
    },
    {
      "from": 87.89,
      "to": 88.05,
      "speaker": 1,
      "confidence": 0.5,
      "final": false
    },
    {
      "from": 88.05,
      "to": 88.24,
      "speaker": 1,
      "confidence": 0.5,
      "final": false
    },
    {
      "from": 88.24,
      "to": 88.32,
      "speaker": 1,
      "confidence": 0.5,
      "final": false
    },
    {
      "from": 88.32,
      "to": 88.6,
      "speaker": 1,
      "confidence": 0.5,
      "final": false
    },
    {
      "from": 88.6,
      "to": 88.78,
      "speaker": 1,
      "confidence": 0.5,
      "final": false
    },
    {
      "from": 88.78,
      "to": 89.18,
      "speaker": 1,
      "confidence": 0.5,
      "final": false
    },
    {
      "from": 89.23,
      "to": 89.39,
      "speaker": 1,
      "confidence": 0.53,
      "final": false
    },
    {
      "from": 89.39,
      "to": 89.51,
      "speaker": 1,
      "confidence": 0.53,
      "final": false
    },
    {
      "from": 89.51,
      "to": 90.01,
      "speaker": 1,
      "confidence": 0.53,
      "final": false
    },
    {
      "from": 90.01,
      "to": 90.23,
      "speaker": 1,
      "confidence": 0.53,
      "final": false
    },
    {
      "from": 90.23,
      "to": 90.91,
      "speaker": 1,
      "confidence": 0.53,
      "final": false
    },
    {
      "from": 90.98,
      "to": 91.33,
      "speaker": 1,
      "confidence": 0.49,
      "final": false
    },
    {
      "from": 91.33,
      "to": 91.81,
      "speaker": 1,
      "confidence": 0.49,
      "final": false
    },
    {
      "from": 91.81,
      "to": 91.94,
      "speaker": 1,
      "confidence": 0.49,
      "final": false
    },
    {
      "from": 91.94,
      "to": 92.18,
      "speaker": 1,
      "confidence": 0.49,
      "final": false
    },
    {
      "from": 92.18,
      "to": 92.31,
      "speaker": 1,
      "confidence": 0.49,
      "final": false
    },
    {
      "from": 92.31,
      "to": 92.88,
      "speaker": 1,
      "confidence": 0.49,
      "final": false
    },
    {
      "from": 92.88,
      "to": 93.1,
      "speaker": 1,
      "confidence": 0.49,
      "final": false
    },
    {
      "from": 93.1,
      "to": 93.54,
      "speaker": 1,
      "confidence": 0.49,
      "final": false
    },
    {
      "from": 93.54,
      "to": 93.71,
      "speaker": 1,
      "confidence": 0.49,
      "final": false
    },
    {
      "from": 93.71,
      "to": 93.87,
      "speaker": 1,
      "confidence": 0.49,
      "final": false
    },
    {
      "from": 93.87,
      "to": 94.35,
      "speaker": 1,
      "confidence": 0.49,
      "final": false
    },
    {
      "from": 94.35,
      "to": 94.73,
      "speaker": 1,
      "confidence": 0.49,
      "final": false
    },
    {
      "from": 94.73,
      "to": 95.39,
      "speaker": 1,
      "confidence": 0.49,
      "final": false
    },
    {
      "from": 95.82,
      "to": 95.99,
      "speaker": 1,
      "confidence": 0.55,
      "final": false
    },
    {
      "from": 95.99,
      "to": 96.36,
      "speaker": 1,
      "confidence": 0.55,
      "final": false
    },
    {
      "from": 96.36,
      "to": 96.59,
      "speaker": 1,
      "confidence": 0.55,
      "final": false
    },
    {
      "from": 96.59,
      "to": 96.75,
      "speaker": 1,
      "confidence": 0.55,
      "final": false
    },
    {
      "from": 96.75,
      "to": 97.06,
      "speaker": 1,
      "confidence": 0.55,
      "final": false
    },
    {
      "from": 97.06,
      "to": 97.12,
      "speaker": 1,
      "confidence": 0.55,
      "final": false
    },
    {
      "from": 97.12,
      "to": 97.21,
      "speaker": 1,
      "confidence": 0.55,
      "final": false
    },
    {
      "from": 97.21,
      "to": 97.61,
      "speaker": 1,
      "confidence": 0.55,
      "final": false
    },
    {
      "from": 97.61,
      "to": 98.22,
      "speaker": 1,
      "confidence": 0.55,
      "final": false
    },
    {
      "from": 98.22,
      "to": 98.56,
      "speaker": 1,
      "confidence": 0.55,
      "final": false
    },
    {
      "from": 98.56,
      "to": 99.14,
      "speaker": 1,
      "confidence": 0.55,
      "final": false
    },
    {
      "from": 99.37,
      "to": 99.5,
      "speaker": 1,
      "confidence": 0.47,
      "final": false
    },
    {
      "from": 99.5,
      "to": 99.61,
      "speaker": 1,
      "confidence": 0.47,
      "final": false
    },
    {
      "from": 99.61,
      "to": 99.95,
      "speaker": 1,
      "confidence": 0.47,
      "final": false
    },
    {
      "from": 99.95,
      "to": 100.28,
      "speaker": 1,
      "confidence": 0.47,
      "final": false
    },
    {
      "from": 100.28,
      "to": 100.93,
      "speaker": 1,
      "confidence": 0.47,
      "final": false
    },
    {
      "from": 100.93,
      "to": 101.27,
      "speaker": 1,
      "confidence": 0.47,
      "final": false
    },
    {
      "from": 101.27,
      "to": 101.55,
      "speaker": 1,
      "confidence": 0.47,
      "final": false
    },
    {
      "from": 101.55,
      "to": 101.86,
      "speaker": 1,
      "confidence": 0.47,
      "final": false
    },
    {
      "from": 101.86,
      "to": 101.93,
      "speaker": 1,
      "confidence": 0.47,
      "final": false
    },
    {
      "from": 101.93,
      "to": 102.47,
      "speaker": 1,
      "confidence": 0.47,
      "final": false
    },
    {
      "from": 102.5,
      "to": 103.1,
      "speaker": 1,
      "confidence": 0.43,
      "final": false
    },
    {
      "from": 103.94,
      "to": 104.11,
      "speaker": 1,
      "confidence": 0.5,
      "final": false
    },
    {
      "from": 104.11,
      "to": 104.37,
      "speaker": 1,
      "confidence": 0.5,
      "final": false
    },
    {
      "from": 104.37,
      "to": 104.58,
      "speaker": 1,
      "confidence": 0.5,
      "final": false
    },
    {
      "from": 104.58,
      "to": 105.03,
      "speaker": 1,
      "confidence": 0.5,
      "final": false
    },
    {
      "from": 105.03,
      "to": 105.67,
      "speaker": 1,
      "confidence": 0.5,
      "final": false
    },
    {
      "from": 105.67,
      "to": 105.81,
      "speaker": 1,
      "confidence": 0.5,
      "final": false
    },
    {
      "from": 105.81,
      "to": 106.06,
      "speaker": 1,
      "confidence": 0.5,
      "final": false
    },
    {
      "from": 106.06,
      "to": 106.28,
      "speaker": 1,
      "confidence": 0.5,
      "final": false
    },
    {
      "from": 106.28,
      "to": 106.39,
      "speaker": 1,
      "confidence": 0.5,
      "final": false
    },
    {
      "from": 106.39,
      "to": 106.85,
      "speaker": 1,
      "confidence": 0.5,
      "final": false
    },
    {
      "from": 107.84,
      "to": 108.29,
      "speaker": 1,
      "confidence": 0.47,
      "final": false
    },
    {
      "from": 108.29,
      "to": 108.4,
      "speaker": 1,
      "confidence": 0.47,
      "final": false
    },
    {
      "from": 108.4,
      "to": 108.67,
      "speaker": 1,
      "confidence": 0.47,
      "final": false
    },
    {
      "from": 108.67,
      "to": 109.58,
      "speaker": 1,
      "confidence": 0.47,
      "final": false
    },
    {
      "from": 109.8,
      "to": 109.99,
      "speaker": 1,
      "confidence": 0.36,
      "final": false
    },
    {
      "from": 109.99,
      "to": 111.0,
      "speaker": 1,
      "confidence": 0.36,
      "final": false
    },
    {
      "from": 111.03,
      "to": 111.48,
      "speaker": 1,
      "confidence": 0.53,
      "final": false
    },
    {
      "from": 111.48,
      "to": 111.6,
      "speaker": 1,
      "confidence": 0.53,
      "final": false
    },
    {
      "from": 111.6,
      "to": 111.86,
      "speaker": 1,
      "confidence": 0.53,
      "final": false
    },
    {
      "from": 111.86,
      "to": 112.08,
      "speaker": 1,
      "confidence": 0.53,
      "final": false
    },
    {
      "from": 112.08,
      "to": 112.21,
      "speaker": 1,
      "confidence": 0.53,
      "final": false
    },
    {
      "from": 112.21,
      "to": 112.62,
      "speaker": 1,
      "confidence": 0.53,
      "final": false
    },
    {
      "from": 112.62,
      "to": 112.93,
      "speaker": 1,
      "confidence": 0.53,
      "final": false
    },
    {
      "from": 112.93,
      "to": 113.2,
      "speaker": 1,
      "confidence": 0.53,
      "final": false
    },
    {
      "from": 113.2,
      "to": 113.53,
      "speaker": 1,
      "confidence": 0.53,
      "final": false
    },
    {
      "from": 113.53,
      "to": 113.93,
      "speaker": 1,
      "confidence": 0.53,
      "final": false
    },
    {
      "from": 113.93,
      "to": 114.18,
      "speaker": 1,
      "confidence": 0.53,
      "final": false
    },
    {
      "from": 114.18,
      "to": 114.86,
      "speaker": 1,
      "confidence": 0.53,
      "final": false
    },
    {
      "from": 114.9,
      "to": 115.1,
      "speaker": 1,
      "confidence": 0.42,
      "final": false
    },
    {
      "from": 115.1,
      "to": 115.4,
      "speaker": 1,
      "confidence": 0.42,
      "final": false
    },
    {
      "from": 115.4,
      "to": 115.62,
      "speaker": 1,
      "confidence": 0.42,
      "final": false
    },
    {
      "from": 115.62,
      "to": 115.68,
      "speaker": 1,
      "confidence": 0.42,
      "final": false
    },
    {
      "from": 115.68,
      "to": 116.3,
      "speaker": 1,
      "confidence": 0.42,
      "final": false
    },
    {
      "from": 116.33,
      "to": 116.57,
      "speaker": 1,
      "confidence": 0.54,
      "final": false
    },
    {
      "from": 116.57,
      "to": 116.75,
      "speaker": 1,
      "confidence": 0.54,
      "final": false
    },
    {
      "from": 116.75,
      "to": 116.81,
      "speaker": 1,
      "confidence": 0.54,
      "final": false
    },
    {
      "from": 116.81,
      "to": 117.27,
      "speaker": 1,
      "confidence": 0.54,
      "final": false
    },
    {
      "from": 117.27,
      "to": 117.52,
      "speaker": 1,
      "confidence": 0.54,
      "final": false
    },
    {
      "from": 117.52,
      "to": 117.68,
      "speaker": 1,
      "confidence": 0.54,
      "final": false
    },
    {
      "from": 117.68,
      "to": 117.8,
      "speaker": 1,
      "confidence": 0.54,
      "final": false
    },
    {
      "from": 117.8,
      "to": 118.26,
      "speaker": 1,
      "confidence": 0.54,
      "final": false
    },
    {
      "from": 118.26,
      "to": 118.94,
      "speaker": 1,
      "confidence": 0.54,
      "final": false
    },
    {
      "from": 119.75,
      "to": 120.14,
      "speaker": 1,
      "confidence": 0.47,
      "final": false
    },
    {
      "from": 120.14,
      "to": 120.41,
      "speaker": 1,
      "confidence": 0.47,
      "final": true
    }
  ]
}